{
  "title": "3 Disturbing Natural Oddities",
  "segments": [
    {
      "text": "Nature sometimes behaves in ways we can’t explain.",
      "keywords": "strange landscape"
    },
    {
      "text": "Certain phenomena occur without any logical reason.",
      "keywords": "natural oddities"
    },
    {
      "text": "Some lakes seem to disappear overnight.",
      "keywords": "vanishing lake"
    },
    {
      "text": "Others glow eerily, leaving scientists unsettled.",
      "keywords": "glowing water"
    },
    {
      "text": "These oddities challenge everything we know.",
      "keywords": "nature mystery"
    },
    {
      "text": "Follow for mysteries we still can't explain.",
      "keywords": "natural phenomena"
    }
  ],
  "description": "Nature has its quirks that leave us all puzzled. Follow for daily mysteries!",
  "hashtags": [
    "#unexplained",
    "#mystery",
    "#nature",
    "#strange",
    "#shorts",
    "#fyp"
  ]
}